Metadata-Version: 2.4
Name: agentrun-operation-sdk
Version: 0.1.1
Summary: AgentRun Operation SDK - A toolkit for agent runtime operations
Author-email: Your Name <your.email@example.com>
License: MIT
Project-URL: Homepage, https://github.com/yourusername/hw-agentrun-sdk-python
Project-URL: Repository, https://github.com/yourusername/hw-agentrun-sdk-python
Project-URL: Issues, https://github.com/yourusername/hw-agentrun-sdk-python/issues
Keywords: agent,runtime,sdk,operations
Classifier: Development Status :: 3 - Alpha
Classifier: Intended Audience :: Developers
Classifier: License :: OSI Approved :: MIT License
Classifier: Programming Language :: Python :: 3
Classifier: Programming Language :: Python :: 3.8
Classifier: Programming Language :: Python :: 3.9
Classifier: Programming Language :: Python :: 3.10
Classifier: Programming Language :: Python :: 3.11
Requires-Python: >=3.8
Requires-Dist: typer
Requires-Dist: rich
Requires-Dist: pydantic
Requires-Dist: prompt-toolkit
